tests/__init__.py
uniqcharstest4-1.0.dist-info/LICENSE
uniqcharstest4-1.0.dist-info/METADATA
uniqcharstest4-1.0.dist-info/WHEEL
uniqcharstest4-1.0.dist-info/entry_points.txt
uniqcharstest4-1.0.dist-info/top_level.txt
uniqcharstest4-1.0.dist-info/RECORD
